agent_integration/__init__.py
agent_integration/client.py
agent_integration/py.typed
mcp_server/__init__.py
mcp_server/config.py
mcp_server/enhanced_server.py
mcp_server/monitoring.py
mcp_server/prometheus.py
mcp_server/server.py
mcp_server/audit/__init__.py
mcp_server/audit/logger.py
mcp_server/auth/__init__.py
mcp_server/auth/decorators.py
mcp_server/auth/jwt_handler.py
mcp_server/auth/rbac.py
mcp_server/auth/token_blacklist.py
mcp_server/database/__init__.py
mcp_server/database/indexes.py
mcp_server/database/models.py
mcp_server/database/neo4j_client.py
mcp_server/database/neo4j_client_enhanced.py
mcp_server/tools/__init__.py
mcp_server/tools/enhanced_exec_tool.py
mcp_server/tools/exec_tool.py
mcp_server/tools/gen_tool.py
mcp_server/tools/graph_tool.py
mcp_server/tools/lint_tool.py
mcp_server/tools/test_tool.py
mcp_server/utils/__init__.py
mcp_server/utils/cache.py
mcp_server/utils/circuit_breaker.py
mcp_server/utils/enhanced_security.py
mcp_server/utils/validation.py
ultimate_mcp-0.1.2.dist-info/licenses/LICENSE
ultimate_mcp-0.1.2.dist-info/METADATA
ultimate_mcp-0.1.2.dist-info/WHEEL
ultimate_mcp-0.1.2.dist-info/top_level.txt
ultimate_mcp-0.1.2.dist-info/RECORD
