Metadata-Version: 2.4
Name: ultimate-mcp
Version: 0.1.2
Summary: Production-ready Model Context Protocol (MCP) stack
Author-email: Your Name <your.email@example.com>
License: MIT
Requires-Python: >=3.11
License-File: LICENSE
Dynamic: license-file
